bavard_nlu/__init__.py
bavard_nlu/auto_setup.py
bavard_nlu/constants.py
bavard_nlu/metrics.py
bavard_nlu/model.py
bavard_nlu/tuner.py
bavard_nlu/utils.py
bavard_nlu/vwci.py
bavard_nlu/cli/__init__.py
bavard_nlu/cli/__main__.py
bavard_nlu/cli/evaluate.py
bavard_nlu/cli/predict.py
bavard_nlu/cli/train.py
bavard_nlu/cli/tune.py
bavard_nlu/data_preprocessing/__init__.py
bavard_nlu/data_preprocessing/nlu_data.py
bavard_nlu/data_preprocessing/training_example.py
bavard_nlu/mlops/__init__.py
bavard_nlu/mlops/deploy.py
bavard_nlu/mlops/pub_sub.py
bavard_nlu-0.0.27.dist-info/DESCRIPTION.rst
bavard_nlu-0.0.27.dist-info/METADATA
bavard_nlu-0.0.27.dist-info/RECORD
bavard_nlu-0.0.27.dist-info/WHEEL
bavard_nlu-0.0.27.dist-info/entry_points.txt
bavard_nlu-0.0.27.dist-info/metadata.json
bavard_nlu-0.0.27.dist-info/top_level.txt
test/__init__.py
test/functional/__init__.py
test/functional/test_auto_setup.py
test/functional/test_data_preprocessor.py
test/functional/test_model.py
test/functional/test_utils.py
test/validation/__init__.py
test/validation/test_performance.py
