Metadata-Version: 2.0
Name: bavard-nlu
Version: 0.0.27
Summary: A library and CLI for NLP tasks
Home-page: https://github.com/bavard-ai/bavard-nlu
Author: Bavard AI, LLC
Author-email: dev@bavard.ai
License: UNKNOWN
Platform: UNKNOWN
Classifier: Programming Language :: Python :: 3
Classifier: License :: OSI Approved :: MIT License
Classifier: Operating System :: OS Independent
Requires-Python: >=3.6
Requires-Dist: transformers (==3.4.0)
Requires-Dist: tensorflow (==2.2.0)
Requires-Dist: scikit-learn (==0.23.2)
Requires-Dist: tensorflow-probability (==0.10.1)
Requires-Dist: uncertainty-metrics (==0.0.81)
Requires-Dist: fire (==0.3.1)
Requires-Dist: keras-tuner (==1.0.1)
Requires-Dist: bavard-ml-common (==0.0.7)
Requires-Dist: uvicorn (==0.12.2)
Requires-Dist: google-cloud-pubsub (==2.1.0)
Requires-Dist: protobuf (==3.12.0)
